auto_denoise-2.0.0.dist-info/licenses/LICENSE
autoden/__init__.py
autoden/__main__.py
autoden/cli.py
autoden/debug.py
autoden/losses.py
autoden/py.typed
autoden/algorithms/__init__.py
autoden/algorithms/deep_image_prior.py
autoden/algorithms/denoiser.py
autoden/algorithms/noise2noise.py
autoden/algorithms/noise2void.py
autoden/algorithms/supervised.py
autoden/models/__init__.py
autoden/models/config.py
autoden/models/dncnn.py
autoden/models/io.py
autoden/models/msd.py
autoden/models/param_utils.py
autoden/models/resnet.py
autoden/models/unet.py
auto_denoise-2.0.0.dist-info/METADATA
auto_denoise-2.0.0.dist-info/WHEEL
auto_denoise-2.0.0.dist-info/entry_points.txt
auto_denoise-2.0.0.dist-info/top_level.txt
auto_denoise-2.0.0.dist-info/RECORD
