Metadata-Version: 2.4
Name: auto-denoise
Version: 2.0.0
Summary: Unsupervised and self-supervised CNN denoising methods.
Author-email: Nicola VIGANO <nicola.vigano@cea.fr>
License-Expression: MIT
Project-URL: Homepage, https://CEA-MetroCarac.github.io/auto-denoise
Project-URL: Documentation, https://CEA-MetroCarac.github.io/auto-denoise
Project-URL: Changelog, https://CEA-MetroCarac.github.io/auto-denoise/changelog
Project-URL: Repository, https://github.com/CEA-MetroCarac/auto-denoise
Project-URL: Issues, https://github.com/CEA-MetroCarac/auto-denoise/issues
Project-URL: Discussions, https://github.com/CEA-MetroCarac/auto-denoise/discussions
Classifier: Development Status :: 4 - Beta
Classifier: Intended Audience :: Developers
Classifier: Programming Language :: Python
Classifier: Programming Language :: Python :: 3
Classifier: Programming Language :: Python :: 3 :: Only
Classifier: Programming Language :: Python :: 3.10
Classifier: Programming Language :: Python :: 3.11
Classifier: Programming Language :: Python :: 3.12
Classifier: Programming Language :: Python :: 3.13
Classifier: Topic :: Documentation
Classifier: Topic :: Software Development
Classifier: Topic :: Utilities
Classifier: Typing :: Typed
Requires-Python: >=3.10
License-File: LICENSE
Requires-Dist: numpy>=1.21
Requires-Dist: scipy
Requires-Dist: tqdm
Requires-Dist: matplotlib
Requires-Dist: imageio
Requires-Dist: scikit-image
Requires-Dist: torch
Provides-Extra: dev
Requires-Dist: editables>=0.5; extra == "dev"
Requires-Dist: build>=1.2; extra == "dev"
Requires-Dist: git-changelog>=2.4; extra == "dev"
Requires-Dist: twine>=5.1; python_version < "3.13" and extra == "dev"
Requires-Dist: isort; extra == "dev"
Requires-Dist: pyupgrade; extra == "dev"
Requires-Dist: pytest>=8.2; extra == "dev"
Requires-Dist: pytest-cov>=5.0; extra == "dev"
Requires-Dist: pytest-randomly>=3.15; extra == "dev"
Requires-Dist: pytest-xdist>=3.6; extra == "dev"
Requires-Dist: mypy>=1.10; extra == "dev"
Requires-Dist: types-markdown>=3.6; extra == "dev"
Requires-Dist: types-pyyaml>=6.0; extra == "dev"
Requires-Dist: flake8; extra == "dev"
Requires-Dist: black>=24.4; extra == "dev"
Requires-Dist: mkdocs>=1.6; extra == "dev"
Requires-Dist: mkdocs-gen-files>=0.4; extra == "dev"
Requires-Dist: mkdocs-git-committers-plugin-2>=2.3; extra == "dev"
Requires-Dist: mkdocs-literate-nav>=0.6; extra == "dev"
Requires-Dist: mkdocs-material>=9.5; extra == "dev"
Requires-Dist: mkdocstrings[python]>=0.25; extra == "dev"
Requires-Dist: tomli>=2.0; python_version < "3.11" and extra == "dev"
Dynamic: license-file
